{
  "id": "Core/EntitySetValue",
  "title": "EntitySetValue Step | Core SDK Documentation",
  "description": "Returns a copy of the entity with this property set. Use this step to easily automate forensic and e-discovery workflows using Phoenix.",
  "source": "@site/steps/Core/EntitySetValue.md",
  "sourceDirName": "Core",
  "slug": "/Core/EntitySetValue",
  "permalink": "/soda/steps/next/Core/EntitySetValue",
  "draft": false,
  "unlisted": false,
  "editUrl": "https://github.com/jimken-mido/soda/steps/Core/EntitySetValue.md",
  "tags": [
    {
      "inline": true,
      "label": "Step",
      "permalink": "/soda/steps/next/tags/step"
    },
    {
      "inline": true,
      "label": "Core",
      "permalink": "/soda/steps/next/tags/core"
    }
  ],
  "version": "current",
  "frontMatter": {
    "title": "EntitySetValue Step | Core SDK Documentation",
    "sidebar_label": "EntitySetValue",
    "description": "Returns a copy of the entity with this property set. Use this step to easily automate forensic and e-discovery workflows using Phoenix.",
    "tags": [
      "Step",
      "Core"
    ],
    "hide_title": true,
    "hide_table_of_contents": true
  },
  "sidebar": "steps",
  "previous": {
    "title": "EntityRemoveProperty",
    "permalink": "/soda/steps/next/Core/EntityRemoveProperty"
  },
  "next": {
    "title": "EntityValidateRelations",
    "permalink": "/soda/steps/next/Core/EntityValidateRelations"
  }
}